odoo10_addon_product_uom_technology-10.0.1.0.1-nspkg.pth
odoo/addons/product_uom_technology/README.rst
odoo/addons/product_uom_technology/__init__.py
odoo/addons/product_uom_technology/__manifest__.py
odoo/addons/product_uom_technology/data/product_uom_categ_data.xml
odoo/addons/product_uom_technology/data/product_uom_data.xml
odoo/addons/product_uom_technology/i18n/product_uom_technology.pot
odoo/addons/product_uom_technology/static/description/icon.png
odoo10_addon_product_uom_technology-10.0.1.0.1.dist-info/METADATA
odoo10_addon_product_uom_technology-10.0.1.0.1.dist-info/WHEEL
odoo10_addon_product_uom_technology-10.0.1.0.1.dist-info/namespace_packages.txt
odoo10_addon_product_uom_technology-10.0.1.0.1.dist-info/top_level.txt
odoo10_addon_product_uom_technology-10.0.1.0.1.dist-info/RECORD
